README.txt
setup.cfg
setup.py
bibdb/__init__.py
bibdb/config.py
bibdb/main.py
bibdb/utils.py
bibdb.egg-info/PKG-INFO
bibdb.egg-info/SOURCES.txt
bibdb.egg-info/dependency_links.txt
bibdb.egg-info/entry_points.txt
bibdb.egg-info/requires.txt
bibdb.egg-info/top_level.txt