Metadata-Version: 1.1
Name: bibdb
Version: 0.1.1
Summary: cross-platform management of bibliography from the command line
Home-page: https://github.com/Palpatineli/bibdb.git
Author: Keji Li
Author-email: mail@keji.li
License: GPLv3.0
Platform: UNKNOWN
Classifier: Development Status :: 4 - Beta
Classifier: Environment :: Console
Classifier: Intended Audience :: End Users/Desktop
Classifier: Intended Audience :: Science/Research
Classifier: License :: OSI Approved :: GNU General Public License v3 (GPLv3)
Classifier: Programming Language :: Python :: 3 :: Only
